{
    "lastRefreshed":  "2026-04-27T13:34:38Z",
    "weeksAnalyzed":  [
                          "Apr 6",
                          "Apr 13",
                          "Apr 20",
                          "Apr 27"
                      ],
    "weekDates":  [
                      "2026-04-06",
                      "2026-04-13",
                      "2026-04-20",
                      "2026-04-27"
                  ],
    "markets":  {
                    "hot":  [
                                {
                                    "name":  "Trenton/Princeton",
                                    "dsm":  "Diana Scully",
                                    "risd":  "",
                                    "sobDelta":  311,
                                    "sobDeltaPct":  15.7,
                                    "fyPacingDelta":  492,
                                    "fyPctBgt":  70.7,
                                    "fyGap":  -2446,
                                    "fyBudget":  8350,
                                    "cumulativeAdds":  0,
                                    "q2PctBgt":  101.1,
                                    "q2Budget":  2265,
                                    "q2PctPY":  106.4
                                },
                                {
                                    "name":  "Tyler",
                                    "dsm":  "Crystal Bradford",
                                    "risd":  "Kathi Kirkland",
                                    "sobDelta":  224,
                                    "sobDeltaPct":  133.3,
                                    "fyPacingDelta":  216,
                                    "fyPctBgt":  105.3,
                                    "fyGap":  40,
                                    "fyBudget":  760,
                                    "cumulativeAdds":  0,
                                    "q2PctBgt":  206.6,
                                    "q2Budget":  190,
                                    "q2PctPY":  259.1
                                },
                                {
                                    "name":  "Cedar Rapids",
                                    "dsm":  "",
                                    "risd":  "Jeroen Corver",
                                    "sobDelta":  63,
                                    "sobDeltaPct":  3.8,
                                    "fyPacingDelta":  151,
                                    "fyPctBgt":  110.4,
                                    "fyGap":  546,
                                    "fyBudget":  5250,
                                    "cumulativeAdds":  0,
                                    "q2PctBgt":  129.8,
                                    "q2Budget":  1313,
                                    "q2PctPY":  161.8
                                },
                                {
                                    "name":  "San Angelo",
                                    "dsm":  "Jennelle Diggs",
                                    "risd":  "Tyler Wille",
                                    "sobDelta":  62,
                                    "sobDeltaPct":  47,
                                    "fyPacingDelta":  62,
                                    "fyPctBgt":  66.1,
                                    "fyGap":  -230,
                                    "fyBudget":  678,
                                    "cumulativeAdds":  0,
                                    "q2PctBgt":  119,
                                    "q2Budget":  163,
                                    "q2PctPY":  130.6
                                },
                                {
                                    "name":  "Shreveport",
                                    "dsm":  "Hillary Doyal",
                                    "risd":  "Kathi Kirkland",
                                    "sobDelta":  54,
                                    "sobDeltaPct":  7.8,
                                    "fyPacingDelta":  58,
                                    "fyPctBgt":  82.1,
                                    "fyGap":  -384,
                                    "fyBudget":  2150,
                                    "cumulativeAdds":  0,
                                    "q2PctBgt":  135.8,
                                    "q2Budget":  548,
                                    "q2PctPY":  151.5
                                },
                                {
                                    "name":  "Poughkeepsie",
                                    "dsm":  "Bryce Clemens",
                                    "risd":  "",
                                    "sobDelta":  44,
                                    "sobDeltaPct":  6.2,
                                    "fyPacingDelta":  65,
                                    "fyPctBgt":  75.3,
                                    "fyGap":  -671,
                                    "fyBudget":  2708,
                                    "cumulativeAdds":  0,
                                    "q2PctBgt":  100.1,
                                    "q2Budget":  758,
                                    "q2PctPY":  102.6
                                },
                                {
                                    "name":  "Rockford",
                                    "dsm":  "Alyssa Salisbury",
                                    "risd":  "Kathi Kirkland",
                                    "sobDelta":  41,
                                    "sobDeltaPct":  5.4,
                                    "fyPacingDelta":  162,
                                    "fyPctBgt":  97.3,
                                    "fyGap":  -64,
                                    "fyBudget":  2377,
                                    "cumulativeAdds":  0,
                                    "q2PctBgt":  120.1,
                                    "q2Budget":  666,
                                    "q2PctPY":  122.2
                                },
                                {
                                    "name":  "Evansville/Owensboro",
                                    "dsm":  "Scott Mauser",
                                    "risd":  "",
                                    "sobDelta":  26,
                                    "sobDeltaPct":  3.2,
                                    "fyPacingDelta":  39,
                                    "fyPctBgt":  62.6,
                                    "fyGap":  -1294,
                                    "fyBudget":  3464,
                                    "cumulativeAdds":  0,
                                    "q2PctBgt":  96.8,
                                    "q2Budget":  871,
                                    "q2PctPY":  110.8
                                },
                                {
                                    "name":  "Portland",
                                    "dsm":  "Tyler Tholl",
                                    "risd":  "",
                                    "sobDelta":  23,
                                    "sobDeltaPct":  3,
                                    "fyPacingDelta":  83,
                                    "fyPctBgt":  55.8,
                                    "fyGap":  -1638,
                                    "fyBudget":  3708,
                                    "cumulativeAdds":  0,
                                    "q2PctBgt":  78.3,
                                    "q2Budget":  1020,
                                    "q2PctPY":  87.2
                                },
                                {
                                    "name":  "Lansing",
                                    "dsm":  "Alixzandra Jyawook",
                                    "risd":  "Kathi Kirkland",
                                    "sobDelta":  20,
                                    "sobDeltaPct":  2.5,
                                    "fyPacingDelta":  57,
                                    "fyPctBgt":  140.9,
                                    "fyGap":  777,
                                    "fyBudget":  1901,
                                    "cumulativeAdds":  0,
                                    "q2PctBgt":  172.4,
                                    "q2Budget":  478,
                                    "q2PctPY":  286.2
                                }
                            ],
                    "cold":  [
                                 {
                                     "name":  "St. George",
                                     "dsm":  "Colton Bybee",
                                     "risd":  "Taylor Wheeler",
                                     "sobDelta":  -253,
                                     "sobDeltaPct":  -28.6,
                                     "fyPacingDelta":  -400,
                                     "fyPctBgt":  166.7,
                                     "fyGap":  907,
                                     "fyBudget":  1360,
                                     "cumulativeAdds":  0,
                                     "q2PctBgt":  186.3,
                                     "q2Budget":  340,
                                     "q2PctPY":  216
                                 },
                                 {
                                     "name":  "Portsmouth",
                                     "dsm":  "Ryan Sheehy",
                                     "risd":  "",
                                     "sobDelta":  -102,
                                     "sobDeltaPct":  -12.7,
                                     "fyPacingDelta":  -338,
                                     "fyPctBgt":  66,
                                     "fyGap":  -1191,
                                     "fyBudget":  3506,
                                     "cumulativeAdds":  0,
                                     "q2PctBgt":  74.2,
                                     "q2Budget":  947,
                                     "q2PctPY":  86
                                 },
                                 {
                                     "name":  "Duluth",
                                     "dsm":  "Kelly Katoski",
                                     "risd":  "Jeroen Corver",
                                     "sobDelta":  -30,
                                     "sobDeltaPct":  -3.2,
                                     "fyPacingDelta":  -62,
                                     "fyPctBgt":  141.3,
                                     "fyGap":  517,
                                     "fyBudget":  1251,
                                     "cumulativeAdds":  0,
                                     "q2PctBgt":  288.6,
                                     "q2Budget":  313,
                                     "q2PctPY":  398.9
                                 },
                                 {
                                     "name":  "Missoula",
                                     "dsm":  "",
                                     "risd":  "",
                                     "sobDelta":  -19,
                                     "sobDeltaPct":  -7.6,
                                     "fyPacingDelta":  17,
                                     "fyPctBgt":  47.7,
                                     "fyGap":  -929,
                                     "fyBudget":  1776,
                                     "cumulativeAdds":  0,
                                     "q2PctBgt":  50.2,
                                     "q2Budget":  459,
                                     "q2PctPY":  54.9
                                 },
                                 {
                                     "name":  "Shore",
                                     "dsm":  "Diana Scully",
                                     "risd":  "",
                                     "sobDelta":  -17,
                                     "sobDeltaPct":  -2.7,
                                     "fyPacingDelta":  -23,
                                     "fyPctBgt":  63.8,
                                     "fyGap":  -986,
                                     "fyBudget":  2720,
                                     "cumulativeAdds":  0,
                                     "q2PctBgt":  71.4,
                                     "q2Budget":  843,
                                     "q2PctPY":  78.8
                                 },
                                 {
                                     "name":  "Wichita Falls",
                                     "dsm":  "Jennelle Diggs",
                                     "risd":  "Tyler Wille",
                                     "sobDelta":  -11,
                                     "sobDeltaPct":  -11.1,
                                     "fyPacingDelta":  -16,
                                     "fyPctBgt":  79.6,
                                     "fyGap":  -86,
                                     "fyBudget":  424,
                                     "cumulativeAdds":  0,
                                     "q2PctBgt":  81.4,
                                     "q2Budget":  108,
                                     "q2PctPY":  153.8
                                 },
                                 {
                                     "name":  "Kalamazoo",
                                     "dsm":  "Angela Todd",
                                     "risd":  "Kathi Kirkland",
                                     "sobDelta":  -6,
                                     "sobDeltaPct":  -2,
                                     "fyPacingDelta":  15,
                                     "fyPctBgt":  71.3,
                                     "fyGap":  -424,
                                     "fyBudget":  1476,
                                     "cumulativeAdds":  0,
                                     "q2PctBgt":  88.2,
                                     "q2Budget":  340,
                                     "q2PctPY":  123.1
                                 },
                                 {
                                     "name":  "Great Falls",
                                     "dsm":  "Michelle Sellers",
                                     "risd":  "Taylor Wheeler",
                                     "sobDelta":  -5,
                                     "sobDeltaPct":  -1,
                                     "fyPacingDelta":  13,
                                     "fyPctBgt":  89.3,
                                     "fyGap":  -189,
                                     "fyBudget":  1765,
                                     "cumulativeAdds":  0,
                                     "q2PctBgt":  105.3,
                                     "q2Budget":  451,
                                     "q2PctPY":  113.7
                                 },
                                 {
                                     "name":  "Lufkin",
                                     "dsm":  "Jeffrey Klein",
                                     "risd":  "Kathi Kirkland",
                                     "sobDelta":  -5,
                                     "sobDeltaPct":  -1.6,
                                     "fyPacingDelta":  -36,
                                     "fyPctBgt":  95.4,
                                     "fyGap":  -50,
                                     "fyBudget":  1100,
                                     "cumulativeAdds":  0,
                                     "q2PctBgt":  104.2,
                                     "q2Budget":  297,
                                     "q2PctPY":  120.4
                                 },
                                 {
                                     "name":  "Lafayette",
                                     "dsm":  "Jennifier Francis",
                                     "risd":  "Kathi Kirkland",
                                     "sobDelta":  -5,
                                     "sobDeltaPct":  -2.3,
                                     "fyPacingDelta":  -20,
                                     "fyPctBgt":  66.2,
                                     "fyGap":  -374,
                                     "fyBudget":  1106,
                                     "cumulativeAdds":  0,
                                     "q2PctBgt":  78.9,
                                     "q2Budget":  265,
                                     "q2PctPY":  128.1
                                 }
                             ],
                    "focus":  [
                                  {
                                      "name":  "Utica",
                                      "dsm":  "Paige Lauback",
                                      "risd":  "",
                                      "fyPctBgt":  37.7,
                                      "fyGap":  -2682,
                                      "fyBudget":  4306,
                                      "q2PctBgt":  30.2,
                                      "q2PctPY":  24.3,
                                      "isAlsoCold":  false
                                  },
                                  {
                                      "name":  "Portland",
                                      "dsm":  "Tyler Tholl",
                                      "risd":  "",
                                      "fyPctBgt":  55.8,
                                      "fyGap":  -1638,
                                      "fyBudget":  3708,
                                      "q2PctBgt":  78.3,
                                      "q2PctPY":  87.2,
                                      "isAlsoCold":  false
                                  },
                                  {
                                      "name":  "Portsmouth",
                                      "dsm":  "Ryan Sheehy",
                                      "risd":  "",
                                      "fyPctBgt":  66,
                                      "fyGap":  -1191,
                                      "fyBudget":  3506,
                                      "q2PctBgt":  74.2,
                                      "q2PctPY":  86,
                                      "isAlsoCold":  true
                                  },
                                  {
                                      "name":  "Atlantic City",
                                      "dsm":  "",
                                      "risd":  "",
                                      "fyPctBgt":  38.9,
                                      "fyGap":  -1131,
                                      "fyBudget":  1850,
                                      "q2PctBgt":  42.7,
                                      "q2PctPY":  45.6,
                                      "isAlsoCold":  false
                                  },
                                  {
                                      "name":  "Shore",
                                      "dsm":  "Diana Scully",
                                      "risd":  "",
                                      "fyPctBgt":  63.8,
                                      "fyGap":  -986,
                                      "fyBudget":  2720,
                                      "q2PctBgt":  71.4,
                                      "q2PctPY":  78.8,
                                      "isAlsoCold":  true
                                  },
                                  {
                                      "name":  "Missoula",
                                      "dsm":  "",
                                      "risd":  "",
                                      "fyPctBgt":  47.7,
                                      "fyGap":  -929,
                                      "fyBudget":  1776,
                                      "q2PctBgt":  50.2,
                                      "q2PctPY":  54.9,
                                      "isAlsoCold":  true
                                  },
                                  {
                                      "name":  "Quad Cities",
                                      "dsm":  "Steven Horinka",
                                      "risd":  "Jeroen Corver",
                                      "fyPctBgt":  58.7,
                                      "fyGap":  -813,
                                      "fyBudget":  1969,
                                      "q2PctBgt":  72.9,
                                      "q2PctPY":  117.8,
                                      "isAlsoCold":  false
                                  },
                                  {
                                      "name":  "Albany",
                                      "dsm":  "John Shea",
                                      "risd":  "",
                                      "fyPctBgt":  62.5,
                                      "fyGap":  -535,
                                      "fyBudget":  1425,
                                      "q2PctBgt":  64.6,
                                      "q2PctPY":  75.5,
                                      "isAlsoCold":  false
                                  },
                                  {
                                      "name":  "Sioux Falls",
                                      "dsm":  "",
                                      "risd":  "",
                                      "fyPctBgt":  62.5,
                                      "fyGap":  -488,
                                      "fyBudget":  1300,
                                      "q2PctBgt":  70.7,
                                      "q2PctPY":  93,
                                      "isAlsoCold":  false
                                  },
                                  {
                                      "name":  "Grand Junction",
                                      "dsm":  "Natalie Redding",
                                      "risd":  "",
                                      "fyPctBgt":  57.8,
                                      "fyGap":  -426,
                                      "fyBudget":  1011,
                                      "q2PctBgt":  60.3,
                                      "q2PctPY":  63.4,
                                      "isAlsoCold":  false
                                  },
                                  {
                                      "name":  "Lawton",
                                      "dsm":  "Jennelle Diggs",
                                      "risd":  "Tyler Wille",
                                      "fyPctBgt":  52.3,
                                      "fyGap":  -417,
                                      "fyBudget":  875,
                                      "q2PctBgt":  40.1,
                                      "q2PctPY":  44.1,
                                      "isAlsoCold":  false
                                  },
                                  {
                                      "name":  "Lafayette",
                                      "dsm":  "Jennifier Francis",
                                      "risd":  "Kathi Kirkland",
                                      "fyPctBgt":  66.2,
                                      "fyGap":  -374,
                                      "fyBudget":  1106,
                                      "q2PctBgt":  78.9,
                                      "q2PctPY":  128.1,
                                      "isAlsoCold":  true
                                  },
                                  {
                                      "name":  "Bozeman",
                                      "dsm":  "Nicholas Ineck",
                                      "risd":  "Taylor Wheeler",
                                      "fyPctBgt":  53,
                                      "fyGap":  -360,
                                      "fyBudget":  765,
                                      "q2PctBgt":  62.2,
                                      "q2PctPY":  83.1,
                                      "isAlsoCold":  false
                                  },
                                  {
                                      "name":  "Lake Charles",
                                      "dsm":  "Hillary Doyal",
                                      "risd":  "Kathi Kirkland",
                                      "fyPctBgt":  49.5,
                                      "fyGap":  -285,
                                      "fyBudget":  565,
                                      "q2PctBgt":  56.7,
                                      "q2PctPY":  77.8,
                                      "isAlsoCold":  false
                                  },
                                  {
                                      "name":  "Casper",
                                      "dsm":  "",
                                      "risd":  "Taylor Wheeler",
                                      "fyPctBgt":  59.8,
                                      "fyGap":  -201,
                                      "fyBudget":  500,
                                      "q2PctBgt":  76.8,
                                      "q2PctPY":  99.3,
                                      "isAlsoCold":  false
                                  }
                              ]
                },
    "dsms":  {
                 "hot":  [
                             {
                                 "name":  "Diana Scully",
                                 "markets":  [
                                                 "Shore",
                                                 "Trenton/Princeton"
                                             ],
                                 "q2Start":  935967,
                                 "q2End":  1284196,
                                 "q2Delta":  348229,
                                 "q2DeltaPct":  37.2
                             },
                             {
                                 "name":  "Crystal Bradford",
                                 "markets":  [
                                                 "Killeen/Temple",
                                                 "Tyler",
                                                 "Victoria"
                                             ],
                                 "q2Start":  1226712,
                                 "q2End":  1525612,
                                 "q2Delta":  298900,
                                 "q2DeltaPct":  24.4
                             },
                             {
                                 "name":  "Nicole Daily",
                                 "markets":  [
                                                 "Tri-Cities",
                                                 "Wenatchee",
                                                 "Yakima"
                                             ],
                                 "q2Start":  952671,
                                 "q2End":  1189568,
                                 "q2Delta":  236897,
                                 "q2DeltaPct":  24.9
                             },
                             {
                                 "name":  "Ryan Sheehy",
                                 "markets":  [
                                                 "New Bedford",
                                                 "Portsmouth"
                                             ],
                                 "q2Start":  2381155,
                                 "q2End":  2590755,
                                 "q2Delta":  209600,
                                 "q2DeltaPct":  8.8
                             },
                             {
                                 "name":  "Alyssa Salisbury",
                                 "markets":  [
                                                 "Rockford"
                                             ],
                                 "q2Start":  1957802,
                                 "q2End":  2164062,
                                 "q2Delta":  206260,
                                 "q2DeltaPct":  10.5
                             },
                             {
                                 "name":  "Scott Mauser",
                                 "markets":  [
                                                 "Evansville/Owensboro"
                                             ],
                                 "q2Start":  1303717,
                                 "q2End":  1401779,
                                 "q2Delta":  98062,
                                 "q2DeltaPct":  7.5
                             },
                             {
                                 "name":  "John Shea",
                                 "markets":  [
                                                 "Albany",
                                                 "Berkshires"
                                             ],
                                 "q2Start":  1108876,
                                 "q2End":  1202126,
                                 "q2Delta":  93250,
                                 "q2DeltaPct":  8.4
                             },
                             {
                                 "name":  "Bryce Clemens",
                                 "markets":  [
                                                 "Poughkeepsie"
                                             ],
                                 "q2Start":  904029,
                                 "q2End":  995629,
                                 "q2Delta":  91600,
                                 "q2DeltaPct":  10.1
                             },
                             {
                                 "name":  "Steven Horinka",
                                 "markets":  [
                                                 "Bismarck",
                                                 "Quad Cities",
                                                 "Quincy/Hannibal"
                                             ],
                                 "q2Start":  1506812,
                                 "q2End":  1595248,
                                 "q2Delta":  88436,
                                 "q2DeltaPct":  5.9
                             },
                             {
                                 "name":  "Tyler Tholl",
                                 "markets":  [
                                                 "Augusta",
                                                 "Portland"
                                             ],
                                 "q2Start":  965723,
                                 "q2End":  1038473,
                                 "q2Delta":  72750,
                                 "q2DeltaPct":  7.5
                             }
                         ],
                 "cold":  [
                              {
                                  "name":  "Colton Bybee",
                                  "markets":  [
                                                  "Sierra Vista",
                                                  "St. George",
                                                  "Williston"
                                              ],
                                  "q2Start":  3080260,
                                  "q2End":  2683060,
                                  "q2Delta":  -397200,
                                  "q2DeltaPct":  -12.9
                              },
                              {
                                  "name":  "Jeffrey Klein",
                                  "markets":  [
                                                  "Lufkin"
                                              ],
                                  "q2Start":  1087607,
                                  "q2End":  1050812,
                                  "q2Delta":  -36795,
                                  "q2DeltaPct":  -3.4
                              },
                              {
                                  "name":  "Jed Knapp",
                                  "markets":  [
                                                  "El Paso"
                                              ],
                                  "q2Start":  825950,
                                  "q2End":  801383,
                                  "q2Delta":  -24567,
                                  "q2DeltaPct":  -3
                              },
                              {
                                  "name":  "Trey Bufkin",
                                  "markets":  [
                                                  "Lubbock"
                                              ],
                                  "q2Start":  916529,
                                  "q2End":  904418,
                                  "q2Delta":  -12111,
                                  "q2DeltaPct":  -1.3
                              },
                              {
                                  "name":  "Kelly Katoski",
                                  "markets":  [
                                                  "Duluth"
                                              ],
                                  "q2Start":  1390978,
                                  "q2End":  1383878,
                                  "q2Delta":  -7100,
                                  "q2DeltaPct":  -0.5
                              },
                              {
                                  "name":  "Jennifier Francis",
                                  "markets":  [
                                                  "Lafayette"
                                              ],
                                  "q2Start":  527248,
                                  "q2End":  525748,
                                  "q2Delta":  -1500,
                                  "q2DeltaPct":  -0.3
                              },
                              {
                                  "name":  "Natalie Redding",
                                  "markets":  [
                                                  "Grand Junction",
                                                  "Montrose"
                                              ],
                                  "q2Start":  815130,
                                  "q2End":  818930,
                                  "q2Delta":  3800,
                                  "q2DeltaPct":  0.5
                              },
                              {
                                  "name":  "Christina Hawkins",
                                  "markets":  [
                                                  "Twin Falls"
                                              ],
                                  "q2Start":  719471,
                                  "q2End":  731471,
                                  "q2Delta":  12000,
                                  "q2DeltaPct":  1.7
                              },
                              {
                                  "name":  "Todd Cross",
                                  "markets":  [
                                                  "Faribault/Owatonna",
                                                  "Rochester MN"
                                              ],
                                  "q2Start":  1084065,
                                  "q2End":  1098021,
                                  "q2Delta":  13956,
                                  "q2DeltaPct":  1.3
                              },
                              {
                                  "name":  "Jilian Watson",
                                  "markets":  [
                                                  "Flint"
                                              ],
                                  "q2Start":  947866,
                                  "q2End":  965566,
                                  "q2Delta":  17700,
                                  "q2DeltaPct":  1.9
                              }
                          ]
             }
}